flagger/__init__.py
flagger/exceptions.py
flagger/flagger.py
flagger/type_parsers.py
tests/__init__.py
tests/test_custom_parser.py
tests/test_flagger.py
easy_flagger-2.0.0.dist-info/LICENSE
easy_flagger-2.0.0.dist-info/METADATA
easy_flagger-2.0.0.dist-info/WHEEL
easy_flagger-2.0.0.dist-info/top_level.txt
easy_flagger-2.0.0.dist-info/RECORD
