Metadata-Version: 2.2
Name: easy-flagger
Version: 2.0.0
Summary: A simple package for a flag parsing
Home-page: https://github.com/Doneeel/easy-flagger
Author: Doneeel
Author-email: doneeel08@gmail.com
Classifier: Programming Language :: Python :: 3
Classifier: License :: OSI Approved :: MIT License
Classifier: Operating System :: OS Independent
Requires-Python: >=3.10
License-File: LICENSE
Dynamic: author
Dynamic: author-email
Dynamic: classifier
Dynamic: description
Dynamic: description-content-type
Dynamic: home-page
Dynamic: requires-python
Dynamic: summary
